d2c_mp_sales_forecaster/D2CMPForecaster.py
d2c_mp_sales_forecaster/__init__.py
d2c_mp_sales_forecaster/config.toml
d2c_mp_sales_forecaster/config/db_ddl.sql
d2c_mp_sales_forecaster/pages/_1_Load_Data.py
d2c_mp_sales_forecaster/pages/_2_Product_Selection.py
d2c_mp_sales_forecaster/pages/_3_Tune_and_Train.py
d2c_mp_sales_forecaster/pages/_4_Forecast_Product.py
d2c_mp_sales_forecaster/pages/_5_Distribute_Size_Forecast.py
d2c_mp_sales_forecaster/pages/__init__.py
d2c_mp_sales_forecaster/utils/__init__.py
d2c_mp_sales_forecaster/utils/db_manager.py
d2c_mp_sales_forecaster-0.0.3.dist-info/METADATA
d2c_mp_sales_forecaster-0.0.3.dist-info/WHEEL
d2c_mp_sales_forecaster-0.0.3.dist-info/licenses/LICENSE
d2c_mp_sales_forecaster-0.0.3.dist-info/RECORD
